<?xml version="1.0" encoding="UTF-8" ?>
<!DOCTYPE mapper PUBLIC "-//mybatis.org//DTD Mapper 3.0//EN" "http://mybatis.org/dtd/mybatis-3-mapper.dtd" >
<mapper namespace="net.mouza.security.dao.RoleInfoMapper">
    <resultMap id="BaseResultMap" type="net.mouza.security.entity.RoleInfo">
        <!--
          WARNING - @mbggenerated
          This element is automatically generated by MyBatis Generator, do not modify.
        -->
        <constructor>
            <idArg column="role_uuid" jdbcType="VARCHAR" javaType="java.lang.String"/>
            <arg column="role_code" jdbcType="VARCHAR" javaType="java.lang.String"/>
            <arg column="role_name" jdbcType="VARCHAR" javaType="java.lang.String"/>
            <arg column="role_desc" jdbcType="VARCHAR" javaType="java.lang.String"/>
        </constructor>
    </resultMap>
    <sql id="Base_Column_List">
        <!--
          WARNING - @mbggenerated
          This element is automatically generated by MyBatis Generator, do not modify.
        -->
        role_uuid, role_code, role_name, role_desc
    </sql>
    <select id="selectByPrimaryKey" resultMap="BaseResultMap" parameterType="java.lang.String">
        <!--
          WARNING - @mbggenerated
          This element is automatically generated by MyBatis Generator, do not modify.
        -->
        select
        <include refid="Base_Column_List"/>
        from role_info
        where role_uuid = #{roleUuid,jdbcType=VARCHAR}
    </select>
    <select id="lists" resultMap="BaseResultMap">
    SELECT * FROM role_info
  </select>
    <select id="selectByCode" resultMap="BaseResultMap">
        select * from role_info i where i.role_code = #{roleCode};
    </select>
    <select id="selectRoleByUsername" resultMap="BaseResultMap">
              SELECT
                r.*
            FROM
                user_role_relations ur ,
                user_info u ,
                role_info r
            WHERE
                ur.user_uuid = u.user_uuid
            AND ur.role_uuid = r.role_uuid
            AND u.user_name = #{username}
    </select>
    <select id="selectRoleByUrl" resultType="net.mouza.security.entity.RoleInfo">
        SELECT
            *
        FROM
            role_resource_relations rrr ,
            role_info role ,
            resource_info res
        WHERE
            rrr.role_uuid = role.role_uuid
        AND rrr.resource_uuid = res.resource_uuid
        AND res.resource_uri = #{url}
    </select>
    <delete id="deleteByPrimaryKey" parameterType="java.lang.String">
        <!--
          WARNING - @mbggenerated
          This element is automatically generated by MyBatis Generator, do not modify.
        -->
        delete from role_info
        where role_uuid = #{roleUuid,jdbcType=VARCHAR}
    </delete>
    <insert id="insert" parameterType="net.mouza.security.entity.RoleInfo">
        <!--
          WARNING - @mbggenerated
          This element is automatically generated by MyBatis Generator, do not modify.
        -->
        insert into role_info (role_uuid, role_code, role_name,
        role_desc)
        values (#{roleUuid,jdbcType=VARCHAR}, #{roleCode,jdbcType=VARCHAR}, #{roleName,jdbcType=VARCHAR},
        #{roleDesc,jdbcType=VARCHAR})
    </insert>
    <insert id="insertSelective" parameterType="net.mouza.security.entity.RoleInfo">
        <!--
          WARNING - @mbggenerated
          This element is automatically generated by MyBatis Generator, do not modify.
        -->
        insert into role_info
        <trim prefix="(" suffix=")" suffixOverrides=",">
            <if test="roleUuid != null">
                role_uuid,
            </if>
            <if test="roleCode != null">
                role_code,
            </if>
            <if test="roleName != null">
                role_name,
            </if>
            <if test="roleDesc != null">
                role_desc,
            </if>
        </trim>
        <trim prefix="values (" suffix=")" suffixOverrides=",">
            <if test="roleUuid != null">
                #{roleUuid,jdbcType=VARCHAR},
            </if>
            <if test="roleCode != null">
                #{roleCode,jdbcType=VARCHAR},
            </if>
            <if test="roleName != null">
                #{roleName,jdbcType=VARCHAR},
            </if>
            <if test="roleDesc != null">
                #{roleDesc,jdbcType=VARCHAR},
            </if>
        </trim>
    </insert>
    <update id="updateByPrimaryKeySelective" parameterType="net.mouza.security.entity.RoleInfo">
        <!--
          WARNING - @mbggenerated
          This element is automatically generated by MyBatis Generator, do not modify.
        -->
        update role_info
        <set>
            <if test="roleCode != null">
                role_code = #{roleCode,jdbcType=VARCHAR},
            </if>
            <if test="roleName != null">
                role_name = #{roleName,jdbcType=VARCHAR},
            </if>
            <if test="roleDesc != null">
                role_desc = #{roleDesc,jdbcType=VARCHAR},
            </if>
        </set>
        where role_uuid = #{roleUuid,jdbcType=VARCHAR}
    </update>
    <update id="updateByPrimaryKey" parameterType="net.mouza.security.entity.RoleInfo">
        <!--
          WARNING - @mbggenerated
          This element is automatically generated by MyBatis Generator, do not modify.
        -->
        update role_info
        set role_code = #{roleCode,jdbcType=VARCHAR},
        role_name = #{roleName,jdbcType=VARCHAR},
        role_desc = #{roleDesc,jdbcType=VARCHAR}
        where role_uuid = #{roleUuid,jdbcType=VARCHAR}
    </update>


</mapper>